tapy/__init__.py
tapy/indicators.py
tapy/utils.py
tapy-1.11.0.dist-info/METADATA
tapy-1.11.0.dist-info/WHEEL
tapy-1.11.0.dist-info/entry_points.txt
tapy-1.11.0.dist-info/licenses/AUTHORS
tapy-1.11.0.dist-info/licenses/LICENSE
tapy-1.11.0.dist-info/RECORD
