Metadata-Version: 2.4
Name: tapy
Version: 1.11.0
Summary: Technical Indicators for the Pandas' Dataframes
Project-URL: Homepage, https://github.com/dmitriiweb/tapy
Author-email: Dmitrii K <dmitriik@proton.me>
License: MIT
License-File: AUTHORS
License-File: LICENSE
Classifier: Development Status :: 5 - Production/Stable
Classifier: Intended Audience :: Developers
Classifier: Intended Audience :: Financial and Insurance Industry
Classifier: License :: OSI Approved :: MIT License
Classifier: Operating System :: OS Independent
Classifier: Programming Language :: Python
Classifier: Programming Language :: Python :: 3
Classifier: Programming Language :: Python :: 3.11
Classifier: Programming Language :: Python :: 3.12
Classifier: Programming Language :: Python :: 3.13
Classifier: Programming Language :: Python :: Implementation :: CPython
Classifier: Topic :: Software Development :: Libraries :: Python Modules
Requires-Python: <4,>=3.11
Requires-Dist: pandas>=2.2
